krajjat/__init__.py
krajjat/analysis_functions.py
krajjat/display_functions.py
krajjat/io_functions.py
krajjat/plot_functions.py
krajjat/stats_functions.py
krajjat/tool_functions.py
krajjat/classes/__init__.py
krajjat/classes/audio.py
krajjat/classes/audio_derivatives.py
krajjat/classes/exceptions.py
krajjat/classes/experiment.py
krajjat/classes/graph_element.py
krajjat/classes/graphic_classes.py
krajjat/classes/joint.py
krajjat/classes/pose.py
krajjat/classes/sequence.py
krajjat/classes/subject.py
krajjat/classes/time_series.py
krajjat/classes/trial.py
krajjat/lib/__init__.py
krajjat/lib/gradients.py
krajjat/res/color_codes.txt
krajjat/res/color_codes_ordered.txt
krajjat/res/color_schemes.txt
krajjat/res/default_steps_gui.txt
krajjat/res/html_colors.txt
krajjat/res/junction_bold.otf
krajjat/res/kinect_joint_labels.txt
krajjat/res/kinect_joints_silhouette_layout.txt
krajjat/res/kinect_joints_subplot_layout.txt
krajjat/res/kinect_skeleton_connections.txt
krajjat/res/kualisys_joint_labels.txt
krajjat/res/kualisys_joints_silhouette_layout.txt
krajjat/res/kualisys_joints_subplot_layout.txt
krajjat/res/kualisys_skeleton_connections.txt
krajjat/res/kualisys_to_kinect.txt
krajjat/res/silhouette.png
krajjat-1.99.21.dist-info/METADATA
krajjat-1.99.21.dist-info/WHEEL
krajjat-1.99.21.dist-info/licenses/LICENSE
krajjat-1.99.21.dist-info/RECORD
