Metadata-Version: 2.4
Name: krajjat
Version: 1.99.21
Summary: Pre-processing, visualisation and analysis of motion capture data and speech
Project-URL: Homepage, https://github.com/RomainPastureau/Krajjat
Project-URL: Bug Tracker, https://github.com/RomainPastureau/Krajjat/issues
Project-URL: Documentation, https://krajjat.readthedocs.io/en/latest/
Project-URL: PyPI, https://pypi.org/project/krajjat/
Author-email: Romain Pastureau <r.pastureau@bcbl.eu>
Maintainer-email: Romain Pastureau <r.pastureau@bcbl.eu>
License-File: LICENSE
Classifier: License :: OSI Approved :: GNU General Public License v3 (GPLv3)
Classifier: Operating System :: OS Independent
Classifier: Programming Language :: Python :: 3
Requires-Python: >=3.7
Requires-Dist: chardet>=5.2.0
Requires-Dist: find-delay>=2.8
Requires-Dist: matplotlib>=3.7
Requires-Dist: numpy>=1.25.0
Requires-Dist: opencv-python>=4.8.0.76
Requires-Dist: openpyxl>=3.1
Requires-Dist: pandas>=2.1.0
Requires-Dist: praat-parselmouth>0.4
Requires-Dist: pyaudio>=0.2.13
Requires-Dist: pygame>=2.5
Requires-Dist: pytaglib>=2.0.0
Requires-Dist: scipy>=1.11.0
Requires-Dist: seaborn>=0.12.21
